<?xml version='1.0' encoding='UTF-8'?><magicdraw><constraint id="f15c70f0-fc9e-46f1-a3f1-767d6fbdf7b0" refElementId="f15c70f0-fc9e-46f1-a3f1-767d6fbdf7b0" humanType="Constraint" classType="Constraint" requireSort="node" icon="index_files/icon_constraint_1169197847.jpg"><documentation humanName="Documentation" mode="s">The UGV must have a neutralization rate sufficient to successfully clear its assigned set of IEDs. Assumption: IED neutralization is evenly divided among UGV.</documentation><visibility humanName="Visibility">public</visibility><specification refid="efff0a1c-fea1-4a27-b50e-c64c9086c9c7" refElementId="efff0a1c-fea1-4a27-b50e-c64c9086c9c7" humanType="Opaque Expression" classType="OpaqueExpression" name="ugvNeutralizationRate >= ((mission.mineNeutralizationRate *       (COUNT(context.ENV.IED)/context.COUNT(UGV)))/mission.missionDuration)" text="ugvNeutralizationRate >= ((mission.mineNeutralizationRate * &#xa;     (COUNT(context.ENV.IED)/context.COUNT(UGV)))/mission.missionDuration)" icon="index_files/icon_opaqueexpression_1144148902.jpg" humanName="Specification" mode="s,e"/><qualifiedName humanName="Qualified Name" mode="e">Systems::UGV::UGV Control Structure::UGV::</qualifiedName><owner refid="ff941efe-feee-4a38-b844-05645b4f6adc" refElementId="ff941efe-feee-4a38-b844-05645b4f6adc" humanType="System" classType="Class" name="UGV" icon="index_files/icon_system_768687341.jpg" humanName="Owner" mode="s,e"/><ownedElement humanName="Owned Element"><comment refid="626c6f29-84c4-4c76-a6c8-903ae5db0fa6" refElementId="626c6f29-84c4-4c76-a6c8-903ae5db0fa6" humanType="Comment" classType="Comment" name="The UGV must have a neutralization rate sufficient..." icon="index_files/icon_comment_734373410.jpg"/><opaqueexpression refid="efff0a1c-fea1-4a27-b50e-c64c9086c9c7" refElementId="efff0a1c-fea1-4a27-b50e-c64c9086c9c7" humanType="Opaque Expression" classType="OpaqueExpression" name="ugvNeutralizationRate >= ((mission.mineNeutralizationRate *       (COUNT(context.ENV.IED)/context.COUNT(UGV)))/mission.missionDuration)" text="ugvNeutralizationRate >= ((mission.mineNeutralizationRate * &#xa;     (COUNT(context.ENV.IED)/context.COUNT(UGV)))/mission.missionDuration)" icon="index_files/icon_opaqueexpression_1144148902.jpg"/></ownedElement><ownedComment humanName="Owned Comment"><comment refid="626c6f29-84c4-4c76-a6c8-903ae5db0fa6" refElementId="626c6f29-84c4-4c76-a6c8-903ae5db0fa6" humanType="Comment" classType="Comment" name="The UGV must have a neutralization rate sufficient..." icon="index_files/icon_comment_734373410.jpg"/></ownedComment><namespace refid="ff941efe-feee-4a38-b844-05645b4f6adc" refElementId="ff941efe-feee-4a38-b844-05645b4f6adc" humanType="System" classType="Class" name="UGV" icon="index_files/icon_system_768687341.jpg" humanName="Namespace"/><name humanName="Name" mode="s,e"></name><context refid="ff941efe-feee-4a38-b844-05645b4f6adc" refElementId="ff941efe-feee-4a38-b844-05645b4f6adc" humanType="System" classType="Class" name="UGV" icon="index_files/icon_system_768687341.jpg" humanName="Context"/><constrainedElement humanName="Constrained Element" mode="s,e"><valueproperty refid="37b2caf0-3104-457d-b5e0-e5207ac3dcd3" refElementId="37b2caf0-3104-457d-b5e0-e5207ac3dcd3" humanType="Value Property" classType="Property" name="ugvNeutralizationRate" icon="index_files/icon_valueproperty_770695165.jpg"/></constrainedElement><TO_DO humanName="To Do" mode="s,e"></TO_DO><ActiveHyperlink humanName="Active Hyperlink"></ActiveHyperlink><report_appliedStereotype_tags humanName="Applied Stereotype" requireSort="element" mode="e"/></constraint></magicdraw>